fp/__init__.py
fp/analysis/__init__.py
fp/analysis/bseq.py
fp/analysis/dft.py
fp/analysis/elph.py
fp/analysis/eqp.py
fp/analysis/esd.py
fp/analysis/esf.py
fp/analysis/kpts.py
fp/analysis/xct.py
fp/analysis/xctph.py
fp/analysis/xctpol.py
fp/data/create.txt
fp/data/flow_CO.yml
fp/data/flow_Cs2AgInCl6.yml
fp/data/flow_Cs2PbI2Cl2.yml
fp/data/flow_Si.yml
fp/data/plot.txt
fp/data/remove.txt
fp/data/orbitals/abacus/Ag.orb
fp/data/orbitals/abacus/Al.orb
fp/data/orbitals/abacus/Ar.orb
fp/data/orbitals/abacus/As.orb
fp/data/orbitals/abacus/Au.orb
fp/data/orbitals/abacus/B.orb
fp/data/orbitals/abacus/Ba.orb
fp/data/orbitals/abacus/Be.orb
fp/data/orbitals/abacus/Bi.orb
fp/data/orbitals/abacus/Br.orb
fp/data/orbitals/abacus/C.orb
fp/data/orbitals/abacus/Ca.orb
fp/data/orbitals/abacus/Cd.orb
fp/data/orbitals/abacus/Cl.orb
fp/data/orbitals/abacus/Co.orb
fp/data/orbitals/abacus/Cr.orb
fp/data/orbitals/abacus/Cs.orb
fp/data/orbitals/abacus/Cu.orb
fp/data/orbitals/abacus/F.orb
fp/data/orbitals/abacus/Fe.orb
fp/data/orbitals/abacus/Ga.orb
fp/data/orbitals/abacus/Ge.orb
fp/data/orbitals/abacus/H.orb
fp/data/orbitals/abacus/He.orb
fp/data/orbitals/abacus/Hf.orb
fp/data/orbitals/abacus/Hg.orb
fp/data/orbitals/abacus/I.orb
fp/data/orbitals/abacus/In.orb
fp/data/orbitals/abacus/Ir.orb
fp/data/orbitals/abacus/K.orb
fp/data/orbitals/abacus/Kr.orb
fp/data/orbitals/abacus/Li.orb
fp/data/orbitals/abacus/Mg.orb
fp/data/orbitals/abacus/Mn.orb
fp/data/orbitals/abacus/Mo.orb
fp/data/orbitals/abacus/N.orb
fp/data/orbitals/abacus/Na.orb
fp/data/orbitals/abacus/Nb.orb
fp/data/orbitals/abacus/Ne.orb
fp/data/orbitals/abacus/Ni.orb
fp/data/orbitals/abacus/O.orb
fp/data/orbitals/abacus/Os.orb
fp/data/orbitals/abacus/P.orb
fp/data/orbitals/abacus/Pb.orb
fp/data/orbitals/abacus/Pd.orb
fp/data/orbitals/abacus/Pt.orb
fp/data/orbitals/abacus/Rb.orb
fp/data/orbitals/abacus/Re.orb
fp/data/orbitals/abacus/Rh.orb
fp/data/orbitals/abacus/Ru.orb
fp/data/orbitals/abacus/S.orb
fp/data/orbitals/abacus/Sb.orb
fp_workflow-2.2.6.dist-info/METADATA
fp_workflow-2.2.6.dist-info/WHEEL
fp_workflow-2.2.6.dist-info/top_level.txt
fp_workflow-2.2.6.dist-info/RECORD
