Metadata-Version: 2.2
Name: fp_workflow
Version: 2.2.6
Summary: First priciples workflow and utilities
Author: Krishnaa Vadivel
Author-email: krishnaa.vadivel@yale.edu
Requires: numpy
Requires: scipy
Requires: ase
Requires: dill
Requires: pyyaml
Requires: cython
Dynamic: author
Dynamic: author-email
Dynamic: description
Dynamic: description-content-type
Dynamic: requires
Dynamic: summary
